Metadata-Version: 1.1
Name: wpxredisorm
Version: 1.0.1
Summary: a package use orm to operate redis
Home-page: http://www.wupengxin.com
Author: wupengxin
Author-email: 15645060726@163.com
License: MIT
Keywords: redis python orm
Platform: UNKNOWN
Classifier: License :: OSI Approved :: MIT License
Classifier: Programming Language :: Python
Classifier: Intended Audience :: Developers
Classifier: Operating System :: OS Independent
